char_pic/__init__.py
char_pic/start.py
README.md
requirements.txt
char_pic-0.1.5.dist-info/entry_points.txt
char_pic-0.1.5.dist-info/WHEEL
char_pic-0.1.5.dist-info/METADATA
char_pic-0.1.5.dist-info/RECORD
